README.md
setup.cfg
setup.py
togif.py
togif.egg-info/PKG-INFO
togif.egg-info/SOURCES.txt
togif.egg-info/dependency_links.txt
togif.egg-info/entry_points.txt
togif.egg-info/requires.txt
togif.egg-info/top_level.txt