Metadata-Version: 2.1
Name: togif
Version: 1.0.2
Summary: UNKNOWN
Home-page: http://github.com/wkentaro/togif
Author: Kentaro Wada
Author-email: www.kentaro.wada@gmail.com
License: UNKNOWN
Platform: UNKNOWN
